py_bootstrap/__init__.py
py_bootstrap/config.py
py_bootstrap/log.py
py_bootstrap-0.0.15.dist-info/METADATA
py_bootstrap-0.0.15.dist-info/WHEEL
py_bootstrap-0.0.15.dist-info/top_level.txt
py_bootstrap-0.0.15.dist-info/RECORD
