Metadata-Version: 2.1
Name: py-bootstrap
Version: 0.0.15
Summary: python端启动器
Home-page: https://github.com/MyCupOfTeaOo/py_bootstrap
Author: zouwendi
Author-email: tz310200@gamil.com
Maintainer: zouwendi
Maintainer-email: tz310200@gamil.com
License: GPL3 License
Platform: all
Classifier: Development Status :: 4 - Beta
Classifier: Operating System :: OS Independent
Classifier: Intended Audience :: Developers
Classifier: Programming Language :: Python
Classifier: Programming Language :: Python :: Implementation
Classifier: Programming Language :: Python :: 3
Classifier: Programming Language :: Python :: 3.4
Classifier: Programming Language :: Python :: 3.5
Classifier: Programming Language :: Python :: 3.5
Classifier: Programming Language :: Python :: 3.6
Classifier: Programming Language :: Python :: 3.7
Classifier: Topic :: Software Development :: Libraries
Requires-Dist: colorama (>=0.4.4)
Requires-Dist: qg-eureka (>=0.0.1)
Requires-Dist: pipreqs (>=0.4.10)
Requires-Dist: requests (>=2.25.1)
Requires-Dist: python-logstash (>=0.4.6)
Requires-Dist: termcolor (>=1.1.0)
Requires-Dist: qg-tool (>=0.0.2)
